spherinator/__init__.py
spherinator/main.py
spherinator/callbacks/__init__.py
spherinator/callbacks/log_reconstruction_callback.py
spherinator/data/__init__.py
spherinator/data/images_data_module.py
spherinator/data/images_dataset.py
spherinator/data/mnist_data_module.py
spherinator/data/parquet_data_module.py
spherinator/data/parquet_dataset.py
spherinator/data/parquet_dataset_sampling.py
spherinator/data/parquet_dataset_with_error.py
spherinator/data/parquet_iterable_data_module.py
spherinator/data/parquet_iterable_dataset.py
spherinator/data/preprocessing.py
spherinator/distributions/__init__.py
spherinator/distributions/power_spherical.py
spherinator/distributions/truncated_normal.py
spherinator/distributions/truncated_normal_distribution.py
spherinator/models/__init__.py
spherinator/models/autoencoder.py
spherinator/models/consecutive_conv_1d_layers.py
spherinator/models/consecutive_conv_2d_layers.py
spherinator/models/consecutive_conv_transpose_1d_layers.py
spherinator/models/consecutive_conv_transpose_2d_layers.py
spherinator/models/convolutional_decoder_1d.py
spherinator/models/convolutional_decoder_2d.py
spherinator/models/convolutional_encoder_1d.py
spherinator/models/convolutional_encoder_2d.py
spherinator/models/dense_model.py
spherinator/models/embedding_reconstruction.py
spherinator/models/export_onnx.py
spherinator/models/variational_autoencoder.py
spherinator/models/weights_provider.py
spherinator/models/yaml2model.py
spherinator-0.4.0.dist-info/licenses/LICENSE
spherinator-0.4.0.dist-info/METADATA
spherinator-0.4.0.dist-info/WHEEL
spherinator-0.4.0.dist-info/entry_points.txt
spherinator-0.4.0.dist-info/top_level.txt
spherinator-0.4.0.dist-info/RECORD
