Metadata-Version: 2.4
Name: spherinator
Version: 0.4.0
Summary: Rotation-Invariant Hyperspherical Variational Convolutional Autoencoder
Author-email: Kai Polsterer <kai.polsterer@h-its.org>, Bernd Doser <bernd.doser@h-its.org>, Andreas Fehlner <andreas.fehlner@h-its.org>, "Sebastian T. Gomez" <sebastian.trujillogomez@h-its.org>
License-Expression: Apache-2.0
Requires-Python: <4.0,>=3.10
License-File: LICENSE
Requires-Dist: jsonargparse[signatures]>=4.37
Requires-Dist: lightning>=2.1
Requires-Dist: matplotlib>=3.10
Requires-Dist: numpy<3.0,>=2.2
Requires-Dist: onnx>=1.15
Requires-Dist: onnxscript>=0.3
Requires-Dist: pandas>=2.1
Requires-Dist: power-spherical>=0.8
Requires-Dist: scikit-image>=0.25
Requires-Dist: scipy>=1.11
Requires-Dist: torch>=2.2
Requires-Dist: torchvision>=0.20
Requires-Dist: gaiaxpy>=2.1
Requires-Dist: pyarrow>=19.0
Requires-Dist: wandb>=0.20
Requires-Dist: sphinxcontrib-bibtex>=2.6.3
Provides-Extra: dev
Requires-Dist: ipykernel>=6.29; extra == "dev"
Requires-Dist: pytest>=8.3; extra == "dev"
Requires-Dist: ruff>=0.11; extra == "dev"
Provides-Extra: extra
Requires-Dist: jupytext>=1.15; extra == "extra"
Requires-Dist: pip-licenses>=5.0; extra == "extra"
Requires-Dist: pytest-cov>=6.1; extra == "extra"
Requires-Dist: scikit-learn>=1.3; extra == "extra"
Requires-Dist: tensorboard>=2.15; extra == "extra"
Provides-Extra: docs
Requires-Dist: myst-parser>=4.0; extra == "docs"
Requires-Dist: recommonmark>=0.7; extra == "docs"
Requires-Dist: sphinx>=8.1; extra == "docs"
Requires-Dist: sphinx-autodoc-typehints>=2.5; extra == "docs"
Requires-Dist: sphinx-rtd-theme>=3.0; extra == "docs"
Requires-Dist: sphinxcontrib-bibtex>=2.6.3; extra == "docs"
Dynamic: license-file
